tests/integration/__init__.py
tests/integration/test_integration_account_type.py
tests/integration/test_integration_accounts.py
tests/integration/test_integration_article.py
tests/integration/test_integration_article_account_coding.py
tests/integration/test_integration_article_label.py
tests/integration/test_integration_bank_account.py
tests/integration/test_integration_company_settings.py
tests/integration/test_integration_cost_centers.py
tests/integration/test_integration_country.py
tests/integration/test_integration_currency.py
tests/integration/test_integration_customer_invoice_drafts.py
tests/integration/test_integration_customer_label.py
tests/integration/test_integration_customers.py
tests/integration/test_integration_delivery_method.py
tests/integration/test_integration_delivery_term.py
tests/integration/test_integration_fiscal_year.py
tests/integration/test_integration_foreign_payment_codes.py
tests/integration/test_integration_opening_balances.py
tests/integration/test_integration_partner_resource_link.py
tests/integration/test_integration_project.py
tests/integration/test_integration_related_accounts.py
tests/integration/test_integration_supplier.py
tests/integration/test_integration_terms_of_payment.py
tests/integration/test_integration_unit.py
tests/integration/test_integration_user.py
tests/integration/test_integration_vat_code.py
tests/integration/test_integration_vat_report.py
visma/__init__.py
visma/api.py
visma/base.py
visma/cli.py
visma/manager.py
visma/models.py
visma/query.py
visma/test.py
visma/test_query.py
visma/utils.py
visma-0.1.0.dist-info/LICENSE.txt
visma-0.1.0.dist-info/METADATA
visma-0.1.0.dist-info/WHEEL
visma-0.1.0.dist-info/entry_points.txt
visma-0.1.0.dist-info/top_level.txt
visma-0.1.0.dist-info/RECORD
