Metadata-Version: 2.1
Name: visma
Version: 0.1.0
Summary: A Python Client/ORM library for integration to Visma e-Accounting, Visma e-Ekonomi
Home-page: https://github.com/pwitab/visma
Author: Henrik Palmlund Wahlgren @ Palmlund Wahlgren Innovative Technology AB
Author-email: henrik@pwit.se
License: BSD-3
Keywords: accounting,visma,eekonomi
Platform: UNKNOWN
Classifier: Development Status :: 3 - Alpha
Classifier: License :: OSI Approved :: BSD License
Classifier: Natural Language :: English
Classifier: Programming Language :: Python
Classifier: Programming Language :: Python :: 3
Classifier: Programming Language :: Python :: 3 :: Only
Classifier: Programming Language :: Python :: 3.6
Classifier: Topic :: Software Development :: Libraries
Requires-Python: >=3.6
Requires-Dist: marshmallow (>=3.0.0b1)
Requires-Dist: click
Requires-Dist: iso8601
Requires-Dist: requests
